noklam/__init__.py
noklam/_modidx.py
noklam/core.py
noklam-0.0.1.dist-info/LICENSE
noklam-0.0.1.dist-info/METADATA
noklam-0.0.1.dist-info/WHEEL
noklam-0.0.1.dist-info/entry_points.txt
noklam-0.0.1.dist-info/top_level.txt
noklam-0.0.1.dist-info/RECORD
